{
	"id": "8c7879a2-175f-46ea-96e2-ee345f5d4643",
	"name": "AlojamientoEnvironment",
	"values": [
		{
			"key": "URL_PRINCIPAL",
			"value": "https://localhost:7062/api",
			"type": "default",
			"enabled": true
		},
		{
			"key": "items",
			"value": "[\n    {\n        \"nombre\": \"Tomate\",\n        \"codigo\": \"TOM\",\n        \"respuesta\": 200\n    },\n    {\n        \"nombre\": \"Harina\",\n        \"codigo\": \"HAR\",\n        \"respuesta\": 200\n    },\n    {\n        \"nombre\": \"Papa\",\n        \"codigo\": \"PAP\",\n        \"respuesta\": 200\n    },\n    {\n        \"nombre\": \"Cebolla\",\n        \"codigo\": \"CEB\",\n        \"respuesta\": 200\n    },\n    {\n        \"nombre\": \"Zanahoria\",\n        \"codigo\": \"ZAN\",\n        \"respuesta\": 200\n    },\n    {\n        \"nombre\": \"\",\n        \"codigo\": \"ASD\",\n        \"respuesta\": 500\n    }\n]",
			"type": "default",
			"enabled": true
		},
		{
			"key": "indicePaisActual",
			"value": "0",
			"type": "default",
			"enabled": true
		},
		{
			"key": "nombrePaisActual",
			"value": "",
			"type": "any",
			"enabled": true
		},
		{
			"key": "codigoPaisActual",
			"value": "",
			"type": "any",
			"enabled": true
		},
		{
			"key": "paises",
			"value": "[\n    {\n        \"nombre\": \"Argentina2\",\n        \"codigopais\": \"ARG2\",\n        \"respuesta\": 200\n    },\n    {\n        \"nombre\": \"Brasil2\",\n        \"codigopais\": \"BR2\",\n        \"respuesta\": 200\n    },\n    {\n        \"nombre\": \"Colombia2\",\n        \"codigopais\": \"COL2\",\n        \"respuesta\": 200\n    },\n    {\n        \"nombre\": \"Ecuador2\",\n        \"codigopais\": \"ECU2\",\n        \"respuesta\": 200\n    },\n    {\n        \"nombre\": \"Chile2\",\n        \"codigopais\": \"CHI2\",\n        \"respuesta\": 200\n    },\n    {\n        \"nombre\": \"Peru2\",\n        \"codigopais\": \"PER2\",\n        \"respuesta\": 200\n    },\n    {\n        \"nombre\": \"Venezuela2\",\n        \"codigopais\": \"VEN2\",\n        \"respuesta\": 200\n    },\n    {\n        \"nombre\": \"\",\n        \"codigopais\": \"VEN2\",\n        \"respuesta\": 400\n    }\n]",
			"type": "default",
			"enabled": true
		},
		{
			"key": "paisesId",
			"value": "[]",
			"type": "default",
			"enabled": true
		},
		{
			"key": "nombreCiudadActual",
			"value": "",
			"type": "default",
			"enabled": true
		},
		{
			"key": "paisIdActual",
			"value": "",
			"type": "default",
			"enabled": true
		},
		{
			"key": "indiceCiudadActual",
			"value": "0",
			"type": "default",
			"enabled": true
		}
	],
	"_postman_variable_scope": "environment",
	"_postman_exported_at": "2023-08-26T11:31:19.026Z",
	"_postman_exported_using": "Postman/10.17.4-230825-0809"
}